mygame_mahes222/__init__.py
mygame_mahes222/main.py
mygame_mahes222-1.0.1.dist-info/METADATA
mygame_mahes222-1.0.1.dist-info/WHEEL
mygame_mahes222-1.0.1.dist-info/entry_points.txt
mygame_mahes222-1.0.1.dist-info/top_level.txt
mygame_mahes222-1.0.1.dist-info/RECORD
