Metadata-Version: 2.4
Name: mygame_mahes222
Version: 1.0.1
Summary: A fun terminal-based Python game made by Mahes.
Author: Mahes
Requires-Python: >=3.7
Dynamic: author
Dynamic: requires-python
Dynamic: summary
